tronapinet/__init__.py
tronapinet/main.py
tronapinet-0.0.1.dist-info/LICENSE.txt
tronapinet-0.0.1.dist-info/METADATA
tronapinet-0.0.1.dist-info/WHEEL
tronapinet-0.0.1.dist-info/top_level.txt
tronapinet-0.0.1.dist-info/RECORD
