Metadata-Version: 2.1
Name: tronapinet
Version: 0.0.1
Summary: tronapinet library for Python
Author: lanaron
Author-email: giraffe0080@aminating.com
License: MIT
Project-URL: Source Repository, https://github.com
License-File: LICENSE.txt
Requires-Dist: requests
